[
    {
        "name": "Emilio Padrón",
        "strava_name": "Emilio P."
    },
    {
        "name": "Ana Barbara González",
        "strava_name": "Ana Barbara G."
    },
    {
        "name": "Ana Ceci Foulkes",
        "strava_name": "Ana Ceci F."
    },
    {
        "name": "Daniel Llamas",
        "strava_name": "Daniel L."
    },
    {
        "name": "Fredy De León",
        "strava_name": "Fredy D."
    },
    {
        "name": "Gerardo Martínez",
        "strava_name": "Gerardo M."
    },
    {
        "name": "Jose Ge Estrada",
        "strava_name": "Jose Ge E."
    },
    {
        "name": "Maryfer Gama",
        "strava_name": "Maryfer G."
    },
    {
        "name": "Natalia Ortega",
        "strava_name": "Natalia O."
    },
    {
        "name": "Sebastián Gutierrez",
        "strava_name": "Sebastian G."
    },
    {
        "name": "Amado Herrera",
        "strava_name": "Amado H."
    },
    {
        "name": "Marco González",
        "strava_name": "Marco G."
    }
]